starling_theme/__init__.py
starling_theme/breadcrumbs.html
starling_theme/footer.html
starling_theme/layout.html
starling_theme/search.html
starling_theme/searchbox.html
starling_theme/theme.conf
starling_theme/static/css/theme.css
starling_theme-0.1.4.dist-info/LICENSE
starling_theme-0.1.4.dist-info/METADATA
starling_theme-0.1.4.dist-info/WHEEL
starling_theme-0.1.4.dist-info/entry_points.txt
starling_theme-0.1.4.dist-info/top_level.txt
starling_theme-0.1.4.dist-info/RECORD
