Metadata-Version: 2.1
Name: starling-theme
Version: 0.1.4
Summary: Sphinx Theme for the StARLinG Lab.
Home-page: https://github.com/starling-lab/starling-theme/
Author: Alexander L. Hayes
Author-email: alexander@batflyer.net
License: MIT
Platform: UNKNOWN
Classifier: Development Status :: 3 - Alpha
Classifier: Framework :: Sphinx
Classifier: Framework :: Sphinx :: Theme
Classifier: License :: OSI Approved :: MIT License
Classifier: Programming Language :: Python :: 3.6
Classifier: Topic :: Documentation
Requires-Dist: sphinx
